vstats/__init__.py
vstats/_est_test_properties.py
vstats/_welchs_test.py
vstats-0.0.4.dist-info/LICENSE
vstats-0.0.4.dist-info/METADATA
vstats-0.0.4.dist-info/WHEEL
vstats-0.0.4.dist-info/RECORD
