Metadata-Version: 2.1
Name: vstats
Version: 0.0.4
Summary: A small Python package providing tools for statistics
License: MIT
Author: J. Janka
Requires-Python: >=3.8.1,<4.0
Classifier: License :: OSI Approved :: MIT License
Classifier: Programming Language :: Python :: 3
Classifier: Programming Language :: Python :: 3.9
Classifier: Programming Language :: Python :: 3.10
Classifier: Programming Language :: Python :: 3.11
Requires-Dist: numpy (>=1.19.5)
Requires-Dist: pandas (>=1.0.1)
Requires-Dist: scipy (>=1.5.1)
Requires-Dist: statsmodels (>=0.12.0)
